[
    {
        "id": "123e4567-e89b-12d3-a456-426614174000",
        "contents": ["content1", "content2", "content3"]
    },
    {
        "id": "123e4567-e89b-12d3-a456-426614174001",
        "contents": ["content4", "content5", "content6"]
    },
    {
        "id": "b1c2d3e4-f5g6-h7i8-j9k0-lmnopqrstuvw",
        "contents": ["word4", "word5", "word6"]
    },
    {
        "id": "c2d3e4f5-g6h7-i8j9-k0lmnopqrstuvwx",
        "contents": ["word7", "word8", "word9"]
    },
    {
        "id": "d3e4f5g6-h7i8-j9k0l-mnopqrstuvwx1y2z",
        "contents": ["word10", "word11", "word12"]
    }
    
    
    
]